zodbshootout/__init__.py
zodbshootout/__main__.py
zodbshootout/_concurrent.py
zodbshootout/_dbsupport.py
zodbshootout/_pblobobject.py
zodbshootout/_pobject.py
zodbshootout/_profile.py
zodbshootout/_runner.py
zodbshootout/_wrapper.py
zodbshootout/fork.py
zodbshootout/interfaces.py
zodbshootout/main.py
zodbshootout/speedtest.py
zodbshootout/tests/__init__.py
zodbshootout/tests/test__dbsupport.py
zodbshootout/tests/test_fork.py
zodbshootout/tests/test_main.py
zodbshootout-0.8.0.dist-info/METADATA
zodbshootout-0.8.0.dist-info/WHEEL
zodbshootout-0.8.0.dist-info/entry_points.txt
zodbshootout-0.8.0.dist-info/namespace_packages.txt
zodbshootout-0.8.0.dist-info/top_level.txt
zodbshootout-0.8.0.dist-info/RECORD
