Metadata-Version: 2.1
Name: zodbshootout
Version: 0.8.0
Summary: A ZODB performance test
Home-page: http://zodbshootout.readthedocs.io
Author: Shane Hathaway
Author-email: shane@hathawaymix.org
Maintainer: Jason Madden
Maintainer-email: jason@nextthought.com
License: ZPL
Keywords: ZODB ZEO RelStorage benchmark
Platform: Any
Classifier: Programming Language :: Python :: 2.7
Classifier: Programming Language :: Python :: 3.5
Classifier: Programming Language :: Python :: 3.6
Classifier: Programming Language :: Python :: 3.7
Classifier: Programming Language :: Python :: 3.8
Classifier: Programming Language :: Python :: Implementation :: CPython
Classifier: Programming Language :: Python :: Implementation :: PyPy
Classifier: Operating System :: MacOS :: MacOS X
Classifier: Operating System :: POSIX
Classifier: Intended Audience :: Developers
Classifier: Development Status :: 4 - Beta
Classifier: License :: OSI Approved :: Zope Public License
Requires-Dist: objgraph
Requires-Dist: setuptools
Requires-Dist: pyperf
Requires-Dist: ZODB (>=4.4.2)
Requires-Dist: ZEO (>=4.2.0)
Requires-Dist: statistics ; python_version == "2.7"
Provides-Extra: mysql
Requires-Dist: relstorage[mysql] (>=2.0rc1) ; extra == 'mysql'
Requires-Dist: mysqlclient (<1.4,>=1.3.7) ; (platform_python_implementation == "CPython" and python_version >= "3.3" and sys_platform != "win32") and extra == 'mysql'
Provides-Extra: oracle
Requires-Dist: relstorage[oracle] (>=2.0rc1) ; extra == 'oracle'
Provides-Extra: postgresql
Requires-Dist: relstorage[postgresql] (>=2.0rc1) ; extra == 'postgresql'
Provides-Extra: test
Requires-Dist: zope.testrunner ; extra == 'test'
Requires-Dist: nti.testing ; extra == 'test'
